py_experimenter/__init__.py
py_experimenter/config.py
py_experimenter/database_connector.py
py_experimenter/database_connector_lite.py
py_experimenter/database_connector_mysql.py
py_experimenter/exceptions.py
py_experimenter/experiment_status.py
py_experimenter/experimenter.py
py_experimenter/result_processor.py
py_experimenter/utils.py
py_experimenter-1.4.2.dist-info/AUTHORS.rst
py_experimenter-1.4.2.dist-info/LICENSE
py_experimenter-1.4.2.dist-info/METADATA
py_experimenter-1.4.2.dist-info/WHEEL
py_experimenter-1.4.2.dist-info/RECORD
