Metadata-Version: 2.1
Name: py-experimenter
Version: 1.4.2
Summary: The PyExperimenter is a tool for the automatic execution of experiments, e.g. for machine learning (ML), capturing corresponding results in a unified manner in a database.
Home-page: https://github.com/tornede/py_experimenter
License: MIT
Keywords: python,experiments,database,executor
Author: Tanja Tornede
Author-email: t.tornede@ai.uni-hannover.de
Requires-Python: >=3.9,<4.0
Classifier: Development Status :: 5 - Production/Stable
Classifier: Intended Audience :: Developers
Classifier: Intended Audience :: Science/Research
Classifier: License :: OSI Approved :: MIT License
Classifier: Programming Language :: Python :: 3
Classifier: Programming Language :: Python :: 3.9
Classifier: Programming Language :: Python :: 3.10
Classifier: Programming Language :: Python :: 3.11
Classifier: Programming Language :: Python :: 3.12
Classifier: Programming Language :: Python :: 3.8
Classifier: Topic :: Scientific/Engineering :: Artificial Intelligence
Requires-Dist: codecarbon (>=2.2.1)
Requires-Dist: joblib (>=1.2.0,<2.0.0)
Requires-Dist: jupyterlab (>=3.5.0,<4.0.0)
Requires-Dist: numpy (>=1.15)
Requires-Dist: omegaconf (>=2.3.0,<3.0.0)
Requires-Dist: pandas (>=1.0)
Requires-Dist: pymysql (>=1.0.3,<2.0.0)
Requires-Dist: sshtunnel (>=0.4.0,<0.5.0)
Project-URL: Documentation, https://tornede.github.io/py_experimenter/
Project-URL: Repository, https://github.com/tornede/py_experimenter
